BivittatusDB/BDB_io.py
BivittatusDB/BDB_metadata.py
BivittatusDB/BDB_tb.py
BivittatusDB/BivittatusDB.py
BivittatusDB/__init__.py
BivittatusDB/bdb_aggregate.py
BivittatusDB/bdb_foreign.py
BivittatusDB/encrypt.py
BivittatusDB/menu.py
BivittatusDB/metaclass.py
BivittatusDB/tty_log.py
BivittatusDB/bin/__init__.py
BivittatusDB/bin/lib_bdb_elf.so
BivittatusDB/bin/lib_bdb_win32.dll
BivittatusDB/bin/lib_bdb_win64.dll
bivittatusDB-1.3.0.0.dist-info/LICENSE
bivittatusDB-1.3.0.0.dist-info/METADATA
bivittatusDB-1.3.0.0.dist-info/WHEEL
bivittatusDB-1.3.0.0.dist-info/top_level.txt
bivittatusDB-1.3.0.0.dist-info/RECORD
