Metadata-Version: 2.1
Name: bivittatusDB
Version: 1.3.0.0
Summary: Operator Based Relational Database Management system for python
Home-page: https://github.com/BivittatusDB/BivittatusDB
Author: BivittatusDB
Author-email: harbingeroffire@proton.me
Classifier: Programming Language :: Python :: 3
Classifier: License :: OSI Approved :: MIT License
Classifier: Operating System :: OS Independent
Requires-Python: >=3.6
License-File: LICENSE
Requires-Dist: cryptography ==42.0.8
